qt_material/__init__.py
qt_material/dock_theme.ui
qt_material/hook-qt_material.py
qt_material/fonts/roboto/Roboto-Black.ttf
qt_material/fonts/roboto/Roboto-BlackItalic.ttf
qt_material/fonts/roboto/Roboto-Bold.ttf
qt_material/fonts/roboto/Roboto-BoldItalic.ttf
qt_material/fonts/roboto/Roboto-Italic.ttf
qt_material/fonts/roboto/Roboto-Light.ttf
qt_material/fonts/roboto/Roboto-LightItalic.ttf
qt_material/fonts/roboto/Roboto-Medium.ttf
qt_material/fonts/roboto/Roboto-MediumItalic.ttf
qt_material/fonts/roboto/Roboto-Regular.ttf
qt_material/fonts/roboto/Roboto-Thin.ttf
qt_material/fonts/roboto/Roboto-ThinItalic.ttf
qt_material/fonts/roboto/RobotoCondensed-Bold.ttf
qt_material/fonts/roboto/RobotoCondensed-BoldItalic.ttf
qt_material/fonts/roboto/RobotoCondensed-Italic.ttf
qt_material/fonts/roboto/RobotoCondensed-Light.ttf
qt_material/fonts/roboto/RobotoCondensed-LightItalic.ttf
qt_material/fonts/roboto/RobotoCondensed-Regular.ttf
qt_material/resources/__init__.py
qt_material/resources/generate.py
qt_material/resources/logo/__init__.py
qt_material/resources/logo/logo.svg
qt_material/resources/logo/logo_frame.svg
qt_material/resources/source/__init__.py
qt_material/resources/source/base.svg
qt_material/resources/source/branch-closed.svg
qt_material/resources/source/branch-end.svg
qt_material/resources/source/branch-more.svg
qt_material/resources/source/branch-open.svg
qt_material/resources/source/checkbox_checked.svg
qt_material/resources/source/checkbox_checked_invert.svg
qt_material/resources/source/checkbox_indeterminate.svg
qt_material/resources/source/checkbox_indeterminate_invert.svg
qt_material/resources/source/checkbox_unchecked.svg
qt_material/resources/source/checkbox_unchecked_invert.svg
qt_material/resources/source/checklist.svg
qt_material/resources/source/checklist_indeterminate.svg
qt_material/resources/source/checklist_indeterminate_invert.svg
qt_material/resources/source/checklist_invert.svg
qt_material/resources/source/close.svg
qt_material-2.16.dist-info/licenses/LICENSE
qt_material-2.16.dist-info/METADATA
qt_material-2.16.dist-info/WHEEL
qt_material-2.16.dist-info/entry_points.txt
qt_material-2.16.dist-info/top_level.txt
qt_material-2.16.dist-info/RECORD
