Metadata-Version: 2.4
Name: qt-material
Version: 2.16
Summary: Material inspired stylesheet for PySide6 and PyQt6.
Author-email: Yeison Cardona <yencardonaal@unal.edu.co>
Maintainer-email: Yeison Cardona <yencardonaal@unal.edu.co>
License: BSD-2-Clause
Project-URL: Homepage, https://github.com/dunderlab/qt-material
Project-URL: Download, https://github.com/dunderlab/qt-material/releases/latest
Project-URL: Documentation, https://qt-material.readthedocs.io/en/latest/
Project-URL: Repository, https://github.com/dunderlab/qt-material.git
Project-URL: Issues, https://github.com/dunderlab/qt-material/issues
Classifier: Development Status :: 5 - Production/Stable
Classifier: License :: OSI Approved :: BSD License
Classifier: Programming Language :: Python :: 3.13
Classifier: Programming Language :: Python :: 3.12
Classifier: Programming Language :: Python :: 3.11
Classifier: Programming Language :: Python :: 3.10
Classifier: Programming Language :: Python :: 3.9
Classifier: Programming Language :: Python :: 3.8
Requires-Python: >=3.7
License-File: LICENSE
Requires-Dist: Jinja2
Dynamic: license-file
